MANIFEST.in
README.md
requirements.txt
setup.py
InstaLiveCLI/InstaLiveCLI.py
InstaLiveCLI/__init__.py
InstaLiveCLI/http.py
InstaLiveCLI/util.py
InstaLiveCLI.egg-info/PKG-INFO
InstaLiveCLI.egg-info/SOURCES.txt
InstaLiveCLI.egg-info/dependency_links.txt
InstaLiveCLI.egg-info/requires.txt
InstaLiveCLI.egg-info/top_level.txt