Metadata-Version: 2.1
Name: InstaLiveCLI
Version: 1.0.2
Summary: InstaLiveCLI is a Python CLI that create a Instagram Live and provide you a rtmp server and stream key to streaming using sofwares like OBS-Studio.
Home-page: https://github.com/RaihanStark/instalivecli
Author: Raihan Yudo Saputra
Author-email: raihanyudosaputra30@gmail.com
License: GPL-3.0
Project-URL: Example, https://github.com/RaihanStark/instalivecli/blob/master/live_broadcast.py
Project-URL: Bug Reports, https://github.com/RaihanStark/instalivecli/issues
Platform: UNKNOWN
Requires-Python: >=3.8
